darklim-0.1.3.dist-info/METADATA
darklim-0.1.3.dist-info/LICENSE
darklim-0.1.3.dist-info/WHEEL
darklim-0.1.3.dist-info/top_level.txt
darklim-0.1.3.dist-info/RECORD
darklim.libs/libquadmath-e2ac3af2.so.0.0.0
darklim.libs/libgfortran-a8535147.so.5.0.0
darklim/__init__.py
darklim/constants/_constants.py
darklim/constants/__init__.py
darklim/sensitivity/_random_sampling.py
darklim/sensitivity/__init__.py
darklim/sensitivity/_plotting.py
darklim/sensitivity/_sens_est.py
darklim/limit/__init__.py
darklim/limit/_limit.py
darklim/limit/_upper/y_vs_CLf.txt
darklim/limit/_upper/Cm.txt
darklim/limit/_upper/CMax.txt
darklim/limit/_upper/CMaxf.txt
darklim/limit/_upper/upper.cpython-36m-i386-linux-gnu.so
darklim/limit/_upper/ymintable.txt
