Metadata-Version: 2.1
Name: darklim
Version: 0.1.3
Summary: DM Limit Setting and Sensitivity
Home-page: https://github.com/spice-herald/darklim
Author: Samuel Watkins
Author-email: samwatkins@berkeley.edu
License: UNKNOWN
Platform: UNKNOWN
License-File: LICENSE
Requires-Dist: numpy
Requires-Dist: scipy
Requires-Dist: matplotlib
Requires-Dist: mendeleev
Requires-Dist: scikit-learn
